etc_player/__init__.py
etc_player/admin.py
etc_player/apps.py
etc_player/management/__init__.py
etc_player/management/commands/__init__.py
etc_player/management/commands/play_audio.py
etc_player/migrations/0001_initial.py
etc_player/migrations/__init__.py
etc_player/models.py
etc_player/ops/audio.service
etc_player/ops/audio.socket
etc_player/ops/player.nginx
etc_player/ops/player.py
etc_player/ops/player.service
etc_player/ops/player.socket
etc_player/player.py
etc_player/settings.py
etc_player/static/bootstrap/css/bootstrap-grid.css
etc_player/static/bootstrap/css/bootstrap-grid.css.map
etc_player/static/bootstrap/css/bootstrap-grid.min.css
etc_player/static/bootstrap/css/bootstrap-grid.min.css.map
etc_player/static/bootstrap/css/bootstrap-grid.rtl.css
etc_player/static/bootstrap/css/bootstrap-grid.rtl.css.map
etc_player/static/bootstrap/css/bootstrap-grid.rtl.min.css
etc_player/static/bootstrap/css/bootstrap-grid.rtl.min.css.map
etc_player/static/bootstrap/css/bootstrap-reboot.css
etc_player/static/bootstrap/css/bootstrap-reboot.css.map
etc_player/static/bootstrap/css/bootstrap-reboot.min.css
etc_player/static/bootstrap/css/bootstrap-reboot.min.css.map
etc_player/static/bootstrap/css/bootstrap-reboot.rtl.css
etc_player/static/bootstrap/css/bootstrap-reboot.rtl.css.map
etc_player/static/bootstrap/css/bootstrap-reboot.rtl.min.css
etc_player/static/bootstrap/css/bootstrap-reboot.rtl.min.css.map
etc_player/static/bootstrap/css/bootstrap-utilities.css
etc_player/static/bootstrap/css/bootstrap-utilities.css.map
etc_player/static/bootstrap/css/bootstrap-utilities.min.css
etc_player/static/bootstrap/css/bootstrap-utilities.min.css.map
etc_player/static/bootstrap/css/bootstrap-utilities.rtl.css
etc_player/static/bootstrap/css/bootstrap-utilities.rtl.css.map
etc_player/static/bootstrap/css/bootstrap-utilities.rtl.min.css
etc_player/static/bootstrap/css/bootstrap-utilities.rtl.min.css.map
etc_player/static/bootstrap/css/bootstrap.css
etc_player-1.1.0.dist-info/LICENSE
etc_player-1.1.0.dist-info/METADATA
etc_player-1.1.0.dist-info/WHEEL
etc_player-1.1.0.dist-info/entry_points.txt
etc_player-1.1.0.dist-info/RECORD
