Metadata-Version: 2.1
Name: etc-player
Version: 1.1.0
Summary: ETC Design Audio Playlist Player - turn a rasberry pi into a scheduled audio player.
Home-page: https://www.emmatc.com
License: MIT
Keywords: django,museum,audio,player,schedule,raspberry pi
Author: Brian Kohan
Author-email: bckohan@gmail.com
Requires-Python: >=3.9,<4.0
Classifier: Development Status :: 5 - Production/Stable
Classifier: Environment :: Console
Classifier: Framework :: Django
Classifier: Framework :: Django :: 4.2
Classifier: Intended Audience :: Other Audience
Classifier: License :: OSI Approved :: MIT License
Classifier: Natural Language :: English
Classifier: Operating System :: OS Independent
Classifier: Programming Language :: Python
Classifier: Programming Language :: Python :: 3
Classifier: Programming Language :: Python :: 3.9
Classifier: Programming Language :: Python :: 3.10
Classifier: Programming Language :: Python :: 3.11
Classifier: Programming Language :: Python :: 3.12
Classifier: Programming Language :: Python :: 3.13
Classifier: Topic :: Database :: Front-Ends
Classifier: Topic :: Internet :: WWW/HTTP
Classifier: Topic :: Internet :: WWW/HTTP :: Site Management
Classifier: Topic :: Multimedia :: Sound/Audio
Classifier: Topic :: Multimedia :: Sound/Audio :: Players
Classifier: Topic :: Office/Business :: Scheduling
Classifier: Topic :: Software Development :: Libraries
Classifier: Topic :: Software Development :: Libraries :: Python Modules
Requires-Dist: django (>=4.2,<5.0)
Requires-Dist: django-enum (>=1.3.3,<2.0.0)
Requires-Dist: django-typer (>=2.2.2,<3.0.0)
Requires-Dist: enum-properties (>=1.8.0,<2.0.0)
Requires-Dist: gunicorn (>=23.0.0,<24.0.0)
Requires-Dist: rich (>=13.8.0,<14.0.0)
Requires-Dist: tzlocal (>=5.2,<6.0)
Project-URL: Repository, https://github.com/bckohan/etc_design_player
